f2_probe_detector/__init__.py
f2_probe_detector/get_f2_probe_position.py
f2_probe_detector/version.py
f2_probe_detector-0.3.11.data/scripts/get_f2_probe_position
f2_probe_detector-0.3.11.dist-info/METADATA
f2_probe_detector-0.3.11.dist-info/RECORD
f2_probe_detector-0.3.11.dist-info/WHEEL
f2_probe_detector-0.3.11.dist-info/top_level.txt
