Metadata-Version: 2.1
Name: f2-probe-detector
Version: 0.3.11
Summary: Flamingos 2 - Probe Detector
Home-page: https://gitlab.gemini.edu/DRSoftware/gemaux_python/
Author: Bruno Quint
Author-email: bquint@gemini.edu
License: UNKNOWN
Platform: UNKNOWN
Classifier: License :: OSI Approved :: MIT License
Classifier: Programming Language :: Python :: 3.4
Classifier: Programming Language :: Python :: 3.5
Classifier: Programming Language :: Python :: 3.6
